[
  {
    "id": 1,
    "price": 9.1,
    "points": 16.5,
    "title": {
      "ar": "عصير الروسيل 285 مل",
      "tr": "Roselle Juice"
    },
    "img": "FB005_Roselle_285ml.jpg"
  },
  {
    "id": 2,
    "price": 15.1,
    "points": 17,
    "title": {
      "ar": "عصير المورينزي 285 مل",
      "tr": "Morinzhi"
    },
    "img": "FB007_Morinzhi_285ml.jpg"
  },
  {
    "id": 3,
    "price": 11.5,
    "points": 19,
    "title": {
      "ar": "قهوة زهي موكا",
      "tr": "Zhi Mocha"
    },
    "img": "FB034_ZhiMocha.jpg"
  },
  {
    "id": 4,
    "price": 18.5,
    "points": 42.5,
    "title": {
      "ar": "عصير الكورديباين 285 مل",
      "tr": "Cordypine"
    },
    "img": "FB053_Cordypine_285ml.jpg"
  },
  {
    "id": 5,
    "price": 9.2,
    "points": 11,
    "title": {
      "ar": "فهوة زهي كلاسيك",
      "tr": "Zhi Classic Cafe"
    },
    "img": "FB063_ZhiCafe.jpg"
  },
  {
    "id": 6,
    "price": 10.5,
    "points": 11,
    "title": {
      "ar": "قهوة بالكريمة",
      "tr": "Cream Coffee"
    },
    "img": "FB068_CreamCoffee.jpg"
  },
  {
    "id": 7,
    "price": 9.8,
    "points": 11.6,
    "title": {
      "ar": "قهوة زينهو البيضاء",
      "tr": "White Coffee Zhino"
    },
    "img": "FB098_WhiteCoffee.jpg"
  },
  {
    "id": 8,
    "price": 13.1,
    "points": 18,
    "title": {
      "ar": "قهوة عرف الأسد",
      "tr": "Lion's Mane Coffee"
    },
    "img": "FB215_LionsManeCoffee.jpg"
  },
  {
    "id": 9,
    "price": 9.9,
    "points": 11.5,
    "title": {
      "ar": "قهوة لينجزي 3 في 1",
      "tr": "Lingzhi Coffee 3 in 1"
    },
    "img": "FB109_Lingzhi3in1.jpg"
  },
  {
    "id": 10,
    "price": 4.6,
    "points": 7.2,
    "title": {
      "ar": "اندومي سبايروديل",
      "tr": "Spirudle"
    },
    "img": "FB300_Spirudle.jpg"
  },
  {
    "id": 11,
    "price": 6.5,
    "points": 14,
    "title": {
      "ar": "مربى التفاح",
      "tr": "Apple Fermented Jam"
    },
    "img": "FB237_AppleFermentedJam.jpg"
  },
  {
    "id": 12,
    "price": 11.8,
    "points": 16,
    "title": {
      "ar": "شاي أوكا عرف الأسد",
      "tr": "Lion's Mane Oocha"
    },
    "img": "FB250_LionsManeOocha.jpg"
  },
  {
    "id": 13,
    "price": 28.8,
    "points": 36,
    "title": {
      "ar": "عصير انزيم التفاح",
      "tr": "Apple Enzyme Drink"
    },
    "img": "FB206_AppleFruitJuice.jpg"
  },
  {
    "id": 14,
    "price": 9.9,
    "points": 11.5,
    "title": {
      "ar": "القهوة السوداء",
      "tr": "Lingzhi Black Coffee"
    },
    "img": "FB122_BlackCoffee.jpg"
  },
  {
    "id": 15,
    "price": 13.3,
    "points": 15,
    "title": {
      "ar": "كوكوزي",
      "tr": "Cocozhi"
    },
    "img": "FB124_Cocozhi.jpg"
  },
  {
    "id": 16,
    "price": 12.8,
    "points": 12,
    "title": {
      "ar": "قهوة الكوردوسيبس 3 في 1",
      "tr": "Cordyceps Coffee 3 in 1"
    },
    "img": "FB129_DXNCordyceps3in1.jpg"
  },
  {
    "id": 17,
    "price": 8.6,
    "points": 10.5,
    "title": {
      "ar": "الليمونزي",
      "tr": "Lemonzhi"
    },
    "img": "FB155_Lemonzhi.jpg"
  },
  {
    "id": 18,
    "price": 1.8,
    "points": 2.5,
    "title": {
      "ar": "حلوى النعناع/ظرف",
      "tr": "Zhi Mint Plus/Sachet"
    },
    "img": "FB143_ZhimintPlus.jpg"
  },
  {
    "id": 19,
    "price": 20.9,
    "points": 30,
    "title": {
      "ar": "حلوى النعناع/علبة",
      "tr": "Zhi Mint Plus/Box"
    },
    "img": "FB143_ZhimintPlus.jpg"
  },
  {
    "id": 20,
    "price": 27.8,
    "points": 39.5,
    "title": {
      "ar": "الفطر الريشي RG-90",
      "tr": "RG-90"
    },
    "img": "HF001_RG90.jpg"
  },
  {
    "id": 21,
    "price": 22.9,
    "points": 39.5,
    "title": {
      "ar": "الفطر الريشي GL-90",
      "tr": "GL-90"
    },
    "img": "HF003_GL90.jpg"
  },
  {
    "id": 22,
    "price": 40,
    "points": 65,
    "title": {
      "ar": "فطر الكوردوسيبس 60 كبسولة",
      "tr": "Cordyceps capsules 60"
    },
    "img": "HF024_Cordyceps_60.jpg"
  },
  {
    "id": 23,
    "price": 23.5,
    "points": 33,
    "title": {
      "ar": "فطر عرف الأسد 120 حبة",
      "tr": "Lion's Mane Tabletes 120"
    },
    "img": "HF029_LionsMane_120.jpg"
  },
  {
    "id": 24,
    "price": 63.6,
    "points": 70,
    "title": {
      "ar": "مسحوق الفطر الريشي",
      "tr": "Reishi Mushroom Powder 70G"
    },
    "img": "HF041_ReishiMushroomPowder_70g.jpg"
  },
  {
    "id": 25,
    "price": 16.7,
    "points": 20,
    "title": {
      "ar": "اسبيرولينا 120 حبة",
      "tr": "Spirulina tablet 120"
    },
    "img": "HF031_Spirulina_120s.jpg"
  },
  {
    "id": 26,
    "price": 95.6,
    "points": 131.5,
    "title": {
      "ar": "الفطر الريشي RG-360",
      "tr": "RG-360"
    },
    "img": ""
  },
  {
    "id": 27,
    "price": 75.4,
    "points": 131.5,
    "title": {
      "ar": "الفطر الريشي GL-360",
      "tr": "GL-360"
    },
    "img": ""
  },
  {
    "id": 28,
    "price": 55.9,
    "points": 75,
    "title": {
      "ar": "السبايرولينا 500",
      "tr": "Spirulina tablet 500"
    },
    "img": ""
  },
  {
    "id": 29,
    "price": 9,
    "points": 12.5,
    "title": {
      "ar": "شامبو جانوزي",
      "tr": "Ganozhi Shampoo"
    },
    "img": "PC004_Shampoo.jpg"
  },
  {
    "id": 30,
    "price": 9,
    "points": 12.5,
    "title": {
      "ar": "رغوة الجسم جانوزي",
      "tr": "Ganozhi Body Foam"
    },
    "img": "PC005_BodyFoam.jpg"
  },
  {
    "id": 31,
    "price": 6.3,
    "points": 7.5,
    "title": {
      "ar": "معجون أسنان جانوزي",
      "tr": "Ganozhi Toothpaste"
    },
    "img": "PC006_Toothpaste.jpg"
  },
  {
    "id": 32,
    "price": 8.7,
    "points": 11.6,
    "title": {
      "ar": "زيت المساج جانو",
      "tr": "Gano Massage Oil"
    },
    "img": "PC020_MassageOil.jpg"
  },
  {
    "id": 33,
    "price": 6.8,
    "points": 7.5,
    "title": {
      "ar": "كريم شجرة الشاي",
      "tr": "Tea Tree Cream"
    },
    "img": ""
  },
  {
    "id": 34,
    "price": 9.9,
    "points": 10,
    "title": {
      "ar": "مستلزمات السفر",
      "tr": "Toilerise travel kit"
    },
    "img": ""
  },
  {
    "id": 35,
    "price": 3.1,
    "points": 3.75,
    "title": {
      "ar": "صابون جانوزي",
      "tr": "Ganozhi Soap"
    },
    "img": "PC036_Soap.jpg"
  },
  {
    "id": 36,
    "price": 6.5,
    "points": 7.3,
    "title": {
      "ar": "تشوبي زيت الأطفال",
      "tr": "Chubby baby oil"
    },
    "img": ""
  },
  {
    "id": 37,
    "price": 14.6,
    "points": 17,
    "title": {
      "ar": "احمر شفاه (احمر غامق)",
      "tr": "Lipstick-Coco Red"
    },
    "img": ""
  },
  {
    "id": 38,
    "price": 14.6,
    "points": 17,
    "title": {
      "ar": "احمر شفاه (عنابي لؤلؤي)",
      "tr": "Lipstick-Pearly Grape"
    },
    "img": ""
  },
  {
    "id": 39,
    "price": 14.6,
    "points": 17,
    "title": {
      "ar": "احمر شفاه (وردي مرجاني)",
      "tr": "Lipstick-Coral Pink"
    },
    "img": ""
  },
  {
    "id": 40,
    "price": 14.6,
    "points": 17,
    "title": {
      "ar": "احمر شفاه (احمر لؤلؤي)",
      "tr": "Lipstick-Pearly Red"
    },
    "img": ""
  },
  {
    "id": 41,
    "price": 14.6,
    "points": 17,
    "title": {
      "ar": "احمر شفاه (لؤلؤي وردي زهري)",
      "tr": "Lipstick-Pearly Pink"
    },
    "img": ""
  },
  {
    "id": 42,
    "price": 7.1,
    "points": 12,
    "title": {
      "ar": "الوفيرا لوشن للجسم واليد",
      "tr": "Aloe V Hand & Body Lotion"
    },
    "img": ""
  }
]
